[
 { 
   "id":1,
   "title":"Vaso de cristal",
   "description":"cristal ultra resistente",
   "price":2000,"thumbnail":"Not Found",
   "code":"vasocristal",
   "stock":87
   
 },
 { 
   "id":2, 
   "title":"Vaso de cristal",
   "description":"cristal ultra resistente",
   "price":2000,"thumbnail":"Not Found",
   "code":"vasocristal",
   "stock":87
   
 },
 { 
   "id":3,
   "title":"Vaso de cristal",
   "description":"cristal ultra resistente",
   "price":2000,"thumbnail":"Not Found",
   "code":"vasocristal",
   "stock":87
   
 },
 { 
   "id":4,
   "title":"Vaso de cristal",
   "description":"cristal ultra resistente",
   "price":2000,"thumbnail":"Not Found",
   "code":"vasocristal",
   "stock":87
   
 },
 { 
   "id":5,  
   "title":"Vaso de cristal",
   "description":"cristal ultra resistente",
   "price":2000,"thumbnail":"Not Found",
   "code":"vasocristal",
   "stock":87
   
 },
 { 
   "id":6,
   "title":"Vaso de cristal",
   "description":"cristal ultra resistente",
   "price":2000,"thumbnail":"Not Found",
   "code":"vasocristal",
   "stock":87
   
 },
 {
   "id":7, 
   "title":"Vaso de cristal",
   "description":"cristal ultra resistente",
   "price":2000,"thumbnail":"Not Found",
   "code":"vasocristal",
   "stock":87
   
 },
 { 
   "id":8,
   "title":"Vaso de cristal",
   "description":"cristal ultra resistente",
   "price":2000,"thumbnail":"Not Found",
   "code":"vasocristal",
   "stock":87
   
 },
 {
   "id":9,
   "title":"Vaso de cristal",
   "description":"cristal ultra resistente",
   "price":2000,"thumbnail":"Not Found",
   "code":"vasocristal",
   "stock":87
   
 },{
    "id":10,
    "title":"Vaso de cristal",
    "description":"cristal ultra resistente",
    "price":2000,"thumbnail":"Not Found",
    "code":"vasocristal",
    "stock":87
} 
]